cookiecutter_python/__init__.py
cookiecutter_python/__main__.py
cookiecutter_python/_find_lib.py
cookiecutter_python/_logging.py
cookiecutter_python/_logging_config.py
cookiecutter_python/backend/__init__.py
cookiecutter_python/backend/check_server_result.py
cookiecutter_python/backend/error_handling/__init__.py
cookiecutter_python/backend/error_handling/handler_builder.py
cookiecutter_python/backend/generator/__init__.py
cookiecutter_python/backend/generator/generator.py
cookiecutter_python/backend/helpers.py
cookiecutter_python/backend/hosting_services/__init__.py
cookiecutter_python/backend/hosting_services/check_engine.py
cookiecutter_python/backend/hosting_services/check_service.py
cookiecutter_python/backend/hosting_services/check_web_hosting_service.py
cookiecutter_python/backend/hosting_services/checker.py
cookiecutter_python/backend/hosting_services/checkers.py
cookiecutter_python/backend/hosting_services/exceptions.py
cookiecutter_python/backend/hosting_services/extract_name.py
cookiecutter_python/backend/hosting_services/handle_hosting_service_check.py
cookiecutter_python/backend/hosting_services/handler.py
cookiecutter_python/backend/hosting_services/value_extractor.py
cookiecutter_python/backend/hosting_services/web_hosting_service.py
cookiecutter_python/backend/load_config.py
cookiecutter_python/backend/main.py
cookiecutter_python/backend/post_main.py
cookiecutter_python/backend/pre_main.py
cookiecutter_python/backend/proxy.py
cookiecutter_python/backend/request.py
cookiecutter_python/backend/sanitization/__init__.py
cookiecutter_python/backend/sanitization/input_sanitization.py
cookiecutter_python/backend/sanitization/interpreters_support.py
cookiecutter_python/backend/sanitization/string_sanitizers/__init__.py
cookiecutter_python/backend/sanitization/string_sanitizers/base_sanitizer.py
cookiecutter_python/backend/sanitization/string_sanitizers/sanitize_reg_input.py
cookiecutter_python-2.7.1.dist-info/METADATA
cookiecutter_python-2.7.1.dist-info/WHEEL
cookiecutter_python-2.7.1.dist-info/entry_points.txt
cookiecutter_python-2.7.1.dist-info/licenses/LICENSE
cookiecutter_python-2.7.1.dist-info/RECORD
