Metadata-Version: 2.4
Name: cookiecutter_python
Version: 2.7.1
Summary: 1-click Generator of Python Project, from Template with streamlined "DevOps" using a powerful CI/CD Pipeline.
License: AGPL-3.0-only
License-File: LICENSE
Author: Konstantinos Lampridis
Author-email: k.lampridis@hotmail.com
Maintainer: Konstantinos Lampridis
Maintainer-email: k.lampridis@hotmail.com
Requires-Python: >=3.8, <3.13
Classifier: License :: OSI Approved :: GNU Affero General Public License v3
Classifier: Programming Language :: Python :: 3
Classifier: Programming Language :: Python :: 3.8
Classifier: Programming Language :: Python :: 3.9
Classifier: Programming Language :: Python :: 3.10
Classifier: Programming Language :: Python :: 3.11
Classifier: Programming Language :: Python :: 3.12
Provides-Extra: docs
Provides-Extra: docslive
Provides-Extra: test
Provides-Extra: typing
Requires-Dist: attrs (>=23.0.0,<24.0.0)
Requires-Dist: build (>=1.2.2.post1) ; extra == "test"
Requires-Dist: click (>=8,<9)
Requires-Dist: colorama (==0.4.5) ; extra == "docs"
Requires-Dist: cookiecutter (>=2.1.1,<3.0.0)
Requires-Dist: gitpython (>=3.1.30,<4.0.0) ; python_version < "3.13" and python_version >= "3.7"
Requires-Dist: griffe (==1.4.0) ; extra == "docs"
Requires-Dist: jinja2-time (>=0.2.0,<1.0.0)
Requires-Dist: mkdocs (>=1.6.1,<2.0.0) ; extra == "docs"
Requires-Dist: mkdocs-autorefs (==1.2.0) ; extra == "docs"
Requires-Dist: mkdocs-click (==0.8.1) ; extra == "docs"
Requires-Dist: mkdocs-gen-files (==0.5.0) ; extra == "docs"
Requires-Dist: mkdocs-git-revision-date-localized-plugin (>=1.4.5,<2.0.0) ; extra == "docs"
Requires-Dist: mkdocs-literate-nav (==0.6.1) ; extra == "docs"
Requires-Dist: mkdocs-macros-plugin (>=1.3.7,<2.0.0) ; extra == "docs"
Requires-Dist: mkdocs-material (>=9.6.12,<10.0.0) ; extra == "docs"
Requires-Dist: mkdocs-mermaid2-plugin (>=1.2.1,<2.0.0) ; extra == "docs"
Requires-Dist: mkdocstrings (==0.26.1) ; extra == "docs"
Requires-Dist: mkdocstrings-python (==1.11.1) ; extra == "docs"
Requires-Dist: mypy (==1.2.0) ; extra == "typing"
Requires-Dist: myst-parser (>=3.0.1,<5.0.0) ; extra == "docslive"
Requires-Dist: packaging (>=22,<23)
Requires-Dist: pymdown-extensions (>=10.15,<11.0.0) ; extra == "docs"
Requires-Dist: pytest (>=7.2.0,<8.0.0) ; (python_version < "3.13" and python_version >= "3.7") and (extra == "test")
Requires-Dist: pytest (>=7.4.4) ; extra == "typing"
Requires-Dist: pytest-click (>=1.1.0,<1.2.0) ; extra == "test"
Requires-Dist: pytest-cov (>=2.12) ; extra == "test"
Requires-Dist: pytest-explicit (>=1.0.1,<1.1.0) ; extra == "test"
Requires-Dist: pytest-object-getter (>=1.0.1,<2.0.0) ; extra == "test"
Requires-Dist: pytest-requests-futures (==0.9.0) ; extra == "test"
Requires-Dist: pytest-run-subprocess (==0.9.0) ; extra == "test"
Requires-Dist: pytest-xdist (>=1.34) ; extra == "test"
Requires-Dist: pyyaml (>=6.0,<7.0)
Requires-Dist: questionary (>=1.10.0,<2.0.0)
Requires-Dist: requests-futures (>=1.0.0,<2.0.0)
Requires-Dist: rich (>=13.0.0,<14.0.0) ; python_version < "3.13" and python_version >= "3.7"
Requires-Dist: software-patterns (>=1.3.0,<2.0.0)
Requires-Dist: sphinx-autobuild (>=2021.3.14,<2022.0.0) ; extra == "docslive"
Requires-Dist: sphinx-inline-tabs (==2023.4.21) ; extra == "docslive"
Requires-Dist: sphinxcontrib-mermaid (==0.9.2) ; extra == "docslive"
Requires-Dist: sphinxcontrib-spelling (>=7.3.3,<8.0.0) ; extra == "docslive"
Requires-Dist: tornado (>=6.3.3,<7.0.0) ; (python_version < "3.13" and python_version >= "3.8") and (extra == "docslive")
Requires-Dist: types-pyyaml (>=6.0.12.5,<7.0.0.0) ; extra == "typing"
Requires-Dist: types-requests (>=2.27.26,<2.28.0) ; extra == "typing"
